definition_tooling/__init__.py
definition_tooling/api_errors.py
definition_tooling/converter/__init__.py
definition_tooling/converter/cli.py
definition_tooling/converter/converter.py
definition_tooling/converter/tests/__snapshots__/test_converter/test_air_quality[auth-consent].json
definition_tooling/converter/tests/__snapshots__/test_converter/test_air_quality[auth_no-consent].json
definition_tooling/converter/tests/__snapshots__/test_converter/test_air_quality[no-auth_consent].json
definition_tooling/converter/tests/__snapshots__/test_converter/test_air_quality[no-auth_no-consent].json
definition_tooling/converter/tests/__snapshots__/test_converter/test_company_basic_info_errors.json
definition_tooling/converter/tests/__snapshots__/test_converter/test_current_weather_required_headers.json
definition_tooling/converter/tests/__snapshots__/test_converter/test_teapot_deprecated.json
definition_tooling/converter/tests/conftest.py
definition_tooling/converter/tests/data/AirQuality/Current.py
definition_tooling/converter/tests/data/Appliance/CoffeeBrewer.py
definition_tooling/converter/tests/data/Company/BasicInfo.py
definition_tooling/converter/tests/data/Weather/Current/Metric.py
definition_tooling/converter/tests/test_converter.py
definition_tooling/log.py
definition_tooling/validator/__init__.py
definition_tooling/validator/cli.py
definition_tooling/validator/core.py
definition_tooling/validator/errors.py
definition_tooling/validator/tests/conftest.py
definition_tooling/validator/tests/data/CompanyBasicInfo.json
definition_tooling/validator/tests/test_definition_versions.py
definition_tooling/validator/tests/test_definitions.py
definition_tooling/validator/tests/test_utils.py
definition_tooling/validator/utils.py
ioxio_data_product_definition_tooling-0.18.0.dist-info/LICENSE
ioxio_data_product_definition_tooling-0.18.0.dist-info/METADATA
ioxio_data_product_definition_tooling-0.18.0.dist-info/WHEEL
ioxio_data_product_definition_tooling-0.18.0.dist-info/entry_points.txt
ioxio_data_product_definition_tooling-0.18.0.dist-info/RECORD
