Metadata-Version: 2.1
Name: ioxio-data-product-definition-tooling
Version: 0.18.0
Summary: IOXIO Data Product Definition Tooling
Home-page: https://github.com/ioxio-dataspace/ioxio-data-product-definition-tooling
License: BSD-3-Clause
Author: IOXIO Ltd
Requires-Python: >=3.10,<4.0
Classifier: License :: OSI Approved :: BSD License
Classifier: Programming Language :: Python :: 3
Classifier: Programming Language :: Python :: 3.10
Classifier: Programming Language :: Python :: 3.11
Classifier: Programming Language :: Python :: 3.12
Classifier: Programming Language :: Python :: 3.13
Requires-Dist: deepdiff (>=8.6.1,<9.0.0)
Requires-Dist: fastapi (>=0.121.1,<0.122.0)
Requires-Dist: pydantic[email] (>=2.12.4,<3.0.0)
Requires-Dist: semver (>=3.0.4,<4.0.0)
Requires-Dist: typer[all] (>=0.20.0,<0.21.0)
Project-URL: Repository, https://github.com/ioxio-dataspace/ioxio-data-product-definition-tooling
